media_id_parser/__init__.py
media_id_parser/facebook.py
media_id_parser/media_id.py
py_media_id_parser-0.0.2.dist-info/LICENSE
py_media_id_parser-0.0.2.dist-info/METADATA
py_media_id_parser-0.0.2.dist-info/WHEEL
py_media_id_parser-0.0.2.dist-info/top_level.txt
py_media_id_parser-0.0.2.dist-info/RECORD
