Metadata-Version: 2.1
Name: py-media-id-parser
Version: 0.0.2
Summary: A simple library to return media or post ID's from various social links
Home-page: https://github.com/corneliusiv/py-media-id-parser
Author: Cornelius Hairston
Author-email: cornelius.hairston@gmail.com
License: MIT
Platform: any
Classifier: Development Status :: 4 - Beta
Classifier: Intended Audience :: Developers
Classifier: Operating System :: OS Independent
Classifier: Programming Language :: Python
Classifier: Topic :: Software Development :: Libraries :: Python Modules
Requires-Dist: requests (<2.22.0,>=2.21.0)
